autohooks/plugins/insert_license/__init__.py
autohooks/plugins/insert_license/insert_license.py
autohooks_plugin_insert_license-0.1.3.dist-info/LICENSE
autohooks_plugin_insert_license-0.1.3.dist-info/WHEEL
autohooks_plugin_insert_license-0.1.3.dist-info/METADATA
autohooks_plugin_insert_license-0.1.3.dist-info/RECORD
