Metadata-Version: 2.1
Name: autohooks-plugin-insert-license
Version: 0.1.3
Summary: An autohooks plugin to insert license in files with insert_license
License: GPL-3.0-or-later
Keywords: git,hooks,insert_license
Author: Vincent Texier
Author-email: vit@free.fr
Requires-Python: >=3.7.0,<4.0.0
Classifier: License :: OSI Approved :: GNU General Public License v3 or later (GPLv3+)
Classifier: Programming Language :: Python :: 3
Classifier: Programming Language :: Python :: 3.10
Classifier: Programming Language :: Python :: 3.7
Classifier: Programming Language :: Python :: 3.8
Classifier: Programming Language :: Python :: 3.9
Requires-Dist: autohooks (>=21.7.0,<22.0.0)
